gitautopush/__init__.py
gitautopush/gitautopush.py
gitautopush-0.4.1.dist-info/LICENSE
gitautopush-0.4.1.dist-info/METADATA
gitautopush-0.4.1.dist-info/WHEEL
gitautopush-0.4.1.dist-info/entry_points.txt
gitautopush-0.4.1.dist-info/top_level.txt
gitautopush-0.4.1.dist-info/RECORD
