Metadata-Version: 2.1
Name: gitautopush
Version: 0.4.1
Summary: UNKNOWN
Home-page: UNKNOWN
Author: John Lee and Chris Holdgraf
Author-email: choldgraf@berkeley.edu
License: BSD
Platform: UNKNOWN
